MANIFEST.in
README.rst
setup.cfg
setup.py
docs/HISTORY.txt
docs/INSTALL.txt
docs/LICENSE.GPL
docs/LICENSE.txt
sc/__init__.py
sc.pfg.brazilianfields.egg-info/PKG-INFO
sc.pfg.brazilianfields.egg-info/SOURCES.txt
sc.pfg.brazilianfields.egg-info/dependency_links.txt
sc.pfg.brazilianfields.egg-info/entry_points.txt
sc.pfg.brazilianfields.egg-info/namespace_packages.txt
sc.pfg.brazilianfields.egg-info/not-zip-safe
sc.pfg.brazilianfields.egg-info/requires.txt
sc.pfg.brazilianfields.egg-info/top_level.txt
sc/pfg/__init__.py
sc/pfg/brazilianfields/README.txt
sc/pfg/brazilianfields/__init__.py
sc/pfg/brazilianfields/config.py
sc/pfg/brazilianfields/configure.zcml
sc/pfg/brazilianfields/fields.py
sc/pfg/brazilianfields/testing.py
sc/pfg/brazilianfields/version.txt
sc/pfg/brazilianfields/Extensions/Install.py
sc/pfg/brazilianfields/locales/manual.pot
sc/pfg/brazilianfields/locales/rebuild_all.sh
sc/pfg/brazilianfields/locales/sc.pfg.brazilianfields.pot
sc/pfg/brazilianfields/locales/pt_BR/LC_MESSAGES/sc.pfg.brazilianfields.mo
sc/pfg/brazilianfields/locales/pt_BR/LC_MESSAGES/sc.pfg.brazilianfields.po
sc/pfg/brazilianfields/profiles/default/factorytool.xml
sc/pfg/brazilianfields/profiles/default/metadata.xml
sc/pfg/brazilianfields/profiles/default/propertiestool.xml
sc/pfg/brazilianfields/profiles/default/types.xml
sc/pfg/brazilianfields/profiles/default/workflows.xml
sc/pfg/brazilianfields/profiles/default/types/BrPhoneField.xml
sc/pfg/brazilianfields/profiles/default/types/CepField.xml
sc/pfg/brazilianfields/profiles/default/types/CnpjField.xml
sc/pfg/brazilianfields/profiles/default/types/CpfField.xml
sc/pfg/brazilianfields/profiles/default/types/FieldsetFolder.xml
sc/pfg/brazilianfields/profiles/default/types/FormFolder.xml
sc/pfg/brazilianfields/profiles/uninstall/propertiestool.xml
sc/pfg/brazilianfields/profiles/uninstall/types.xml
sc/pfg/brazilianfields/tests/__init__.py
sc/pfg/brazilianfields/tests/test_setup.py