Metadata-Version: 1.0
Name: sc.pfg.brazilianfields
Version: 1.1.1
Summary: A collection Brazilian fields to be used with PloneFormGen
Home-page: https://github.com/collective/sc.pfg.brazilianfields
Author: Simples Consultoria
Author-email: products@simplesconsultoria.com.br
License: GPL
Keywords: plone archetypes FormGen BrFieldsAndWidgets brazil brasil pfg
Platform: UNKNOWN
Classifier: Framework :: Plone
Classifier: Framework :: Plone :: 3.3
Classifier: Framework :: Plone :: 4.0
Classifier: Framework :: Plone :: 4.1
Classifier: Framework :: Zope2
Classifier: Framework :: Zope3
Classifier: Intended Audience :: Developers
Classifier: Natural Language :: Portuguese (Brazilian)
Classifier: Programming Language :: Python
Classifier: Topic :: Software Development :: Libraries :: Python Modules
